mangalib_api-0.0.1.dist-info/licenses/LICENSE
other/endpoints.py
mangalib_api-0.0.1.dist-info/METADATA
mangalib_api-0.0.1.dist-info/WHEEL
mangalib_api-0.0.1.dist-info/top_level.txt
mangalib_api-0.0.1.dist-info/RECORD
