Metadata-Version: 2.4
Name: mangalib-api
Version: 0.0.1
Summary: Unofficial lib sites api (ranobelib.me, mangalib.me, ... )
Author-email: Dial Veleon <dialveleon@gmail.com>
License: MIT
Classifier: Programming Language :: Python :: 3
Classifier: Operating System :: OS Independent
Requires-Python: >=3.12
License-File: LICENSE
Requires-Dist: httpx
Requires-Dist: aiofiles
Requires-Dist: pydantic
Dynamic: license-file
